LogNNet/__init__.py
LogNNet/mlp_evaluation.py
LogNNet/neural_network.py
LogNNet/pso_method.py
LogNNet/utility.py
LogNNet-1.7.dist-info/LICENSE
LogNNet-1.7.dist-info/METADATA
LogNNet-1.7.dist-info/WHEEL
LogNNet-1.7.dist-info/top_level.txt
LogNNet-1.7.dist-info/RECORD
