Metadata-Version: 2.1
Name: LogNNet
Version: 1.7
Summary: This package implements the LogNNet neural network, which uses chaotic transformations in the weight matrix to more effectively recognize patterns in data.
Home-page: https://github.com/izotov93/LogNNet
Author: Yuriy Izotov and Andrei Velichko
Author-email: izotov93@yandex.ru
Classifier: Development Status :: 5 - Production/Stable
Classifier: Programming Language :: Python :: 3.11
Classifier: License :: OSI Approved :: MIT License
Requires-Python: >=3.11
License-File: LICENSE
Requires-Dist: numpy >=2.1.0
Requires-Dist: pandas >=2.2.2
Requires-Dist: scikit-learn >=1.5.1
Requires-Dist: scipy >=1.14.0
Requires-Dist: joblib >=1.4.2
